Homework/n26991784_林宏達_hw1_part1_report/code/alu/ALU.v
`define NOP     5'b01001
`define ADD     5'b00000
`define SUB     5'b00001
`define AND     5'b00010
`define OR      5'b00100
`define XOR     5'b00011
`define SRLI    5'b01001
`define SLLI    5'b01000
`define ROTRI   5'b01011

`timescale 1ns/10ps
module alu(alu_result,alu_overflow,scr1,scr2,opcode,sub_opcode,enable_execute,reset);
  
  output  reg  [31:0] alu_result;
  output  reg         alu_overflow;
  
  input        [31:0] scr1,scr2;
  input        [5:0]  opcode;
  input        [4:0]  sub_opcode;
  input               reset;
  input               enable_execute;
  
  reg          [63:0] rotate;
  reg                 a,b;
  
  always@(*)begin
      if(reset)begin
      alu_result=32'b0;
      alu_overflow=1'b0;
    end  
    
  else if(enable_execute)begin
    case(opcode)
      6'b100000 : case(sub_opcode)
                    `ADD   : begin
                              {a,alu_result[30:0]}=scr1[30:0]+scr2[30:0];
                              {b,alu_result[31]}=scr1[31]+scr2[31]+a;
                              alu_overflow=a^b;
                            end
                    `SUB   : begin
                              {a,alu_result[30:0]}=scr1[30:0]-scr2[30:0];
                              {b,alu_result[31]}=scr1[31]-scr2[31]-a;
                              alu_overflow=a^b;
                            end 
                    `AND   : begin
                              alu_result    = scr1&scr2;
                              alu_overflow  = 1'b0;
                            end
                    `OR    : begin
                              alu_result    = scr1|scr2;
                              alu_overflow  = 1'b0;
                            end
                    `XOR   : begin
                              alu_result    = scr1^scr2;
                              alu_overflow  = 1'b0;
                            end 
                    `SRLI  : begin
                              alu_result    = scr1>>scr2;
                              alu_overflow  = 1'b0;
                            end
                    `SLLI  : begin
                              alu_result    = scr1<<scr2;
                              alu_overflow  = 1'b0;
                            end
                    `ROTRI : begin
                             rotate        = {scr1,scr1}>>scr2;
				             alu_result    = rotate[31:0];
                             alu_overflow  = 1'b0;
                             end 
					`NOP:begin
                              alu_result    = 32'b0;
                              alu_overflow  = 1'b0;
                            end		 
                  default : begin
                              alu_overflow=1'b0;
                              alu_result=32'b0;
                            end
                 endcase   
    6'b101000 : begin
                  {a,alu_result[30:0]}=scr1[30:0]+scr2[30:0];
                  {b,alu_result[31]}=scr1[31]+scr2[31]+a;
                  alu_overflow=a^b;    
                end
    6'b101100 : begin
                  alu_overflow=1'b0;
                  alu_result=scr1|scr2;
                end                
    6'b101011 : begin
                  alu_overflow=1'b0;
                  alu_result=32'b0;
                end 
    default   : begin
                  alu_overflow=1'b0;
                  alu_result=32'b0;
                end  
   endcase                                             
  end 
  else begin
    alu_result=32'b0;
    alu_overflow=1'b0;
  end
end
endmodule

Homework/n26991784_林宏達_hw1_part1_report/code/alu/tb_alu.v
`timescale 1ns/10ps
module t_alu();

  wire  [31:0] alu_result;
  wire         alu_overflow;
  
  reg   [31:0] scr1,scr2;
  reg   [5:0]  opcode;
  reg   [4:0]  sub_opcode;
  reg          reset;
  reg          enable_execute;
   
  
alu M1(alu_result,alu_overflow,scr1,scr2,opcode,sub_opcode,enable_execute,reset);


/*initial begin
  $monitor($time,"result= %d, overflow = %d, scr1 = %d, scr2 = %d, opcode = %d,  sub_opcode = %d, enable_execute = %d,  reset = %d",
                  alu_result,alu_overflow,scr1,scr2,opcode,sub_opcode,enable_execute,reset);
 end*/


initial begin
  
       scr1=32'hFFFFFFFF;scr2=32'hEEEEEEEE;opcode=6'b100000;sub_opcode=5'b01001;enable_execute=0;reset=1;
      
       #10   
       scr1=32'h00000000;scr2=32'h00000000;opcode=6'b100000;sub_opcode=5'b01001;enable_execute=1;reset=0;

       #10   
       scr1=32'h33333333;scr2=32'h44444444;opcode=6'b100000;sub_opcode=5'b00000;enable_execute=1;reset=0;
       
       #10   
       scr1=32'h66666666;scr2=32'h55555555;opcode=6'b100000;sub_opcode=5'b00001;
       
       #10   
       scr1=32'h77777777;scr2=32'h88888888;opcode=6'b100000;sub_opcode=5'b00010;
       
       #10   
       scr1=32'h88888888;scr2=32'h77777777;opcode=6'b100000;sub_opcode=5'b00100;
       
       #10   
       scr1=32'h77777777;scr2=32'h88888888;opcode=6'b100000;sub_opcode=5'b00011;
       
       #10   
       scr1=32'h11110000;scr2=32'h00000004;opcode=6'b100000;sub_opcode=5'b01001;
       
       #10   
       scr1=32'h00001111;scr2=32'h00000004;opcode=6'b100000;sub_opcode=5'b01000;
       
       #10   
       scr1=32'h11111110;scr2=32'h00000004;opcode=6'b100000;sub_opcode=5'b01011;
       
       

end

initial begin
   #500 $finish;
end

initial begin
$dumpfile("alu.vcd");
$dumpvars;
end
endmodule

Homework/n26991784_林宏達_hw1_part1_report/code/alu/alu.vcd
$date
    Oct 14, 2010  13:58:19
$end
$version
    TOOL:	ncsim	08.10-p002
$end
$timescale
    10 ps
$end

$scope module t_alu $end
$var wire     32 !    alu_result [31:0] $end
$var wire      1 "    alu_overflow  $end
$var reg      32 #    scr1 [31:0] $end
$var reg      32 $    scr2 [31:0] $end
$var reg       6 %    opcode [5:0] $end
$var reg       5 &    sub_opcode [4:0] $end
$var reg       1 '    reset  $end
$var reg       1 (    enable_execute  $end

$scope module M1 $end
$var reg      32 )    alu_result [31:0] $end
$var reg       1 *    alu_overflow  $end
$var wire     32 +    scr1 [31:0] $end
$var wire     32 ,    scr2 [31:0] $end
$var wire      6 -    opcode [5:0] $end
$var wire      5 .    sub_opcode [4:0] $end
$var wire      1 /    reset  $end
$var wire      1 0    enable_execute  $end
$var reg      64 1    rotate [63:0] $end
$var reg       1 2    a  $end
$var reg       1 3    b  $end
$upscope $end

$upscope $end

$enddefinitions $end
$dumpvars
b0 !
0"
b11111111111111111111111111111111 #
b11101110111011101110111011101110 $
b100000 %
b1001 &
1'
0(
b0 )
0*
b11111111111111111111111111111111 +
b11101110111011101110111011101110 ,
b100000 -
b1001 .
1/
00
bx 1
x2
x3
$end
#1000
b0 #
b0 $
1(
0'
0/
10
b0 ,
b0 +
#2000
b110011001100110011001100110011 #
b1000100010001000100010001000100 $
b0 &
b0 .
b1000100010001000100010001000100 ,
b110011001100110011001100110011 +
b1110111011101110111011101110111 )
02
03
b1110111011101110111011101110111 !
#3000
b1100110011001100110011001100110 #
b1010101010101010101010101010101 $
b1 &
b1 .
b1010101010101010101010101010101 ,
b1100110011001100110011001100110 +
b10001000100010001000100010001 )
b10001000100010001000100010001 !
#4000
b1110111011101110111011101110111 #
b10001000100010001000100010001000 $
b10 &
b10 .
b10001000100010001000100010001000 ,
b1110111011101110111011101110111 +
b0 )
b0 !
#5000
b10001000100010001000100010001000 #
b1110111011101110111011101110111 $
b100 &
b100 .
b1110111011101110111011101110111 ,
b10001000100010001000100010001000 +
b11111111111111111111111111111111 )
b11111111111111111111111111111111 !
#6000
b1110111011101110111011101110111 #
b10001000100010001000100010001000 $
b11 &
b11 .
b10001000100010001000100010001000 ,
b1110111011101110111011101110111 +
#7000
b10001000100010000000000000000 #
b100 $
b1001 &
b1001 .
b100 ,
b10001000100010000000000000000 +
b1000100010001000000000000 )
b1000100010001000000000000 !
#8000
b1000100010001 #
b1000 &
b1000 .
b1000100010001 +
b10001000100010000 )
b10001000100010000 !
#9000
b10001000100010001000100010000 #
b1011 &
b1011 .
b10001000100010001000100010000 +
b100010001000100010001000100000001000100010001000100010001 1
b1000100010001000100010001 )
b1000100010001000100010001 !
