Homework/n26991784_林宏達_hw1_part1_report/code/RCA/rca.v
`timescale 1ns/10ps
module Add_4bitRCA(ovudsign,ovudunsign,sum,cout,a,b,addsub);
  output  [3:0]   sum;
  output          cout,ovudsign,ovudunsign;
  input   [3:0]   a,b;
  input           addsub;
  wire            c_in2,c_in3,c_in4;
  wire    [3:0]   bout;


xor(bout[0],b[0],addsub);
xor(bout[1],b[1],addsub);
xor(bout[2],b[2],addsub);
xor(bout[3],b[3],addsub);


Add_full M1(sum[0],     c_in2,  a[0],   bout[0],   addsub);
Add_full M2(sum[1],     c_in3,  a[1],   bout[1],   c_in2);
Add_full M3(sum[2],     c_in4,  a[2],   bout[2],   c_in3);
Add_full M4(sum[3],     cout,   a[3],   bout[3],   c_in4);

xor (ovudunsign,cout,addsub);
xor (ovudsign,cout,c_in4);

endmodule

//fulladder
module Add_full(sum,c_out,a,b,c_in);
  output  sum,c_out;
  input   a,b,c_in;
  wire    w1,w2,w3;

Add_half M1(w1,w2,a,b);
Add_half M2(sum,w3,w1,c_in);
xor      (c_out,w3,w2);     

endmodule

//halfadder
module Add_half(sum,c_out,a,b);
  output  c_out,sum;
  input   a,b;

and     (c_out, a,   b);
xor     (sum,   a,   b);

endmodule

Homework/n26991784_林宏達_hw1_part1_report/code/RCA/tb_rca.v
`timescale 1ns/10ps
module t_Add_4bitRCA;
  wire  [3:0]   sum;
  wire          cout,ovudsign,ovudunsign;
  reg   [3:0]   a,b;
  reg           addsub;
  

Add_4bitRCA   M1(ovudsign,ovudunsign,sum,cout,a,b,addsub);

/*initial begin
  $monitor($time,"addsub= %d, a = %d, b = %d, cout = %d, sum = %d,  ovudsign = %d, ovudunsign = %d",
                  addsub,a,b,cout,sum,ovudsign,ovudunsign);

end*/

initial begin
  
        a=0; 
        b=0;
        addsub=1;
#10     a=1;
        b=10;
#10     addsub=0;
        a=4;
        b=5;
#10     addsub=0;
        a=10;
        b=6;
#10     a=1;
        b=2;
        addsub=1;
#10     a=3;
        b=9;
        addsub=0;
#10     a=13;
        b=8;
        addsub=1;
#10     addsub=0;
        a=10;
        b=1;
#10     addsub=0;
        a=0;
        b=9;
#10     addsub=0;
        a=3;
        b=4;
#10     a=7;
        b=3;
        addsub=1;
#10     a=3;
        b=9;
        addsub=0;
#10     a=13;
        b=8;
end
initial begin
  #500 $finish;
end

initial begin
$dumpfile("rca.vcd");
$dumpvars;
end
endmodule

Homework/n26991784_林宏達_hw1_part1_report/code/RCA/rca.vcd
$date
    Oct 14, 2010  14:01:37
$end
$version
    TOOL:	ncsim	08.10-p002
$end
$timescale
    10 ps
$end

$scope module t_Add_4bitRCA $end
$var wire      1 !    sum [3] $end
$var wire      1 "    sum [2] $end
$var wire      1 #    sum [1] $end
$var wire      1 $    sum [0] $end
$var wire      1 %    cout  $end
$var wire      1 &    ovudsign  $end
$var wire      1 '    ovudunsign  $end
$var reg       4 (    a [3:0] $end
$var reg       4 )    b [3:0] $end
$var reg       1 *    addsub  $end

$scope module M1 $end
$var wire      1 !    sum [3] $end
$var wire      1 "    sum [2] $end
$var wire      1 #    sum [1] $end
$var wire      1 $    sum [0] $end
$var wire      1 %    cout  $end
$var wire      1 &    ovudsign  $end
$var wire      1 '    ovudunsign  $end
$var wire      1 +    a [3] $end
$var wire      1 ,    a [2] $end
$var wire      1 -    a [1] $end
$var wire      1 .    a [0] $end
$var wire      1 /    b [3] $end
$var wire      1 0    b [2] $end
$var wire      1 1    b [1] $end
$var wire      1 2    b [0] $end
$var wire      1 3    addsub  $end
$var wire      1 4    c_in2  $end
$var wire      1 5    c_in3  $end
$var wire      1 6    c_in4  $end
$var wire      1 7    bout [3] $end
$var wire      1 8    bout [2] $end
$var wire      1 9    bout [1] $end
$var wire      1 :    bout [0] $end

$scope module M1 $end
$var wire      1 $    sum  $end
$var wire      1 4    c_out  $end
$var wire      1 .    a  $end
$var wire      1 :    b  $end
$var wire      1 3    c_in  $end
$var wire      1 ;    w1  $end
$var wire      1 <    w2  $end
$var wire      1 =    w3  $end

$scope module M1 $end
$var wire      1 <    c_out  $end
$var wire      1 ;    sum  $end
$var wire      1 .    a  $end
$var wire      1 :    b  $end
$upscope $end


$scope module M2 $end
$var wire      1 =    c_out  $end
$var wire      1 $    sum  $end
$var wire      1 ;    a  $end
$var wire      1 3    b  $end
$upscope $end

$upscope $end


$scope module M2 $end
$var wire      1 #    sum  $end
$var wire      1 5    c_out  $end
$var wire      1 -    a  $end
$var wire      1 9    b  $end
$var wire      1 4    c_in  $end
$var wire      1 >    w1  $end
$var wire      1 ?    w2  $end
$var wire      1 @    w3  $end

$scope module M1 $end
$var wire      1 ?    c_out  $end
$var wire      1 >    sum  $end
$var wire      1 -    a  $end
$var wire      1 9    b  $end
$upscope $end


$scope module M2 $end
$var wire      1 @    c_out  $end
$var wire      1 #    sum  $end
$var wire      1 >    a  $end
$var wire      1 4    b  $end
$upscope $end

$upscope $end


$scope module M3 $end
$var wire      1 "    sum  $end
$var wire      1 6    c_out  $end
$var wire      1 ,    a  $end
$var wire      1 8    b  $end
$var wire      1 5    c_in  $end
$var wire      1 A    w1  $end
$var wire      1 B    w2  $end
$var wire      1 C    w3  $end

$scope module M1 $end
$var wire      1 B    c_out  $end
$var wire      1 A    sum  $end
$var wire      1 ,    a  $end
$var wire      1 8    b  $end
$upscope $end


$scope module M2 $end
$var wire      1 C    c_out  $end
$var wire      1 "    sum  $end
$var wire      1 A    a  $end
$var wire      1 5    b  $end
$upscope $end

$upscope $end


$scope module M4 $end
$var wire      1 !    sum  $end
$var wire      1 %    c_out  $end
$var wire      1 +    a  $end
$var wire      1 7    b  $end
$var wire      1 6    c_in  $end
$var wire      1 D    w1  $end
$var wire      1 E    w2  $end
$var wire      1 F    w3  $end

$scope module M1 $end
$var wire      1 E    c_out  $end
$var wire      1 D    sum  $end
$var wire      1 +    a  $end
$var wire      1 7    b  $end
$upscope $end


$scope module M2 $end
$var wire      1 F    c_out  $end
$var wire      1 !    sum  $end
$var wire      1 D    a  $end
$var wire      1 6    b  $end
$upscope $end

$upscope $end

$upscope $end

$upscope $end

$enddefinitions $end
$dumpvars
0!
0"
0#
0$
1%
0&
0'
b0 (
b0 )
1*
0+
0,
0-
0.
0/
00
01
02
13
14
15
16
17
18
19
1:
1;
0<
1=
1>
0?
1@
1A
0B
1C
1D
0E
1F
$end
#1000
b1 (
b1010 )
1/
11
1.
0;
1<
09
07
0D
0>
14
1$
0=
1#
0@
0!
0F
0%
05
1"
0C
0&
1'
06
#2000
0*
b100 (
b101 )
0/
10
01
12
1,
0.
03
0'
1$
1;
0<
0A
1B
16
0"
04
0#
1&
1!
#3000
b1010 (
b110 )
11
02
1+
0,
1-
0>
1A
0B
1D
0:
19
1?
0;
0!
1F
16
0"
0&
0$
15
1C
1%
1'
#4000
b1 (
b10 )
1*
13
00
0+
0-
1.
0;
0>
0?
1D
1'
17
09
1:
1<
05
1"
0C
14
1$
1#
06
0&
1!
0F
0%
#5000
b11 (
b1001 )
0*
03
1/
01
12
1-
1>
0'
08
0$
0A
0#
1@
15
#6000
b1101 (
b1000 )
1*
13
02
1+
1,
0-
1>
0A
1D
0E
0'
07
18
19
1$
1B
16
0&
0!
1F
1%
#7000
0*
b1010 (
b1 )
0/
12
0,
1-
0.
03
0'
08
09
1$
1;
0<
0B
06
04
1#
0@
0&
1!
0F
0%
05
0"
#8000
b0 (
b1001 )
1/
0+
0-
0>
1D
17
0#
#9000
b11 (
b100 )
0/
10
02
1-
1.
1;
0<
1>
0:
18
07
0D
1A
1#
1"
0!
#10000
b111 (
b11 )
1*
13
00
11
12
1,
0A
1B
0'
17
0$
1=
14
1D
16
1"
0&
1F
0#
1@
15
1%
#11000
b11 (
b1001 )
0*
03
1/
01
0,
0A
0B
0'
08
1:
0$
0=
14
0;
1<
06
0&
1!
0F
0%
#12000
b1101 (
b1000 )
02
1+
1,
0-
0>
1A
0D
1E
0:
1;
0<
1%
0!
1"
0C
0#
0@
05
06
1'
04
1$
1&
